dayanara/__init__.py
dayanara/core.py
dayanara/main.py
dayanara/msg_types.py
dayanara/network.py
dayanara/olaf.py
dayanara/peer.py
dayanara/test/test.dayanara.py
dayanara/test/test.network.py
dayanara/test/test.olaf.py
dayanara/test/test.peer.py
dayanara/test/test_core.py
dayanara-0.1.4.dist-info/licenses/LICENCE
dayanara-0.1.4.dist-info/METADATA
dayanara-0.1.4.dist-info/WHEEL
dayanara-0.1.4.dist-info/top_level.txt
dayanara-0.1.4.dist-info/RECORD
