Metadata-Version: 2.4
Name: dayanara
Version: 0.1.4
Summary: A lightweight peer-to-peer networking protocol implementation in Python with bootstrap server support for peer discovery and room-based connections.
Author: Olaf Pedersen
Classifier: License :: OSI Approved :: MIT License
Classifier: Programming Language :: Python :: 3
Classifier: Operating System :: OS Independent
Requires-Python: >=3.8
License-File: LICENCE
Dynamic: license-file
